Workbook

Sheet Presupuesto Total del Proyecto
A1: Concepto | B1: Valor Estimado (COP)
A2: Recursos Humanos. | B2: ='Recursos Humanos.'!G5 -> 7500000
A3: Gastos Administrativos. | B3: ='Gastos Administrativos.'!B12 -> 10800000
A4: Software | B4: =Software.!E5 -> 6606000
A5: Hadware. | B5: =Hadware.!C7 -> 1687500
A6: Ganancia (Utilidad del Proyecto) | B6: ='Gastos Administrativos.'!D16 -> 10000000
A7: Total de Inversión | B7: =SUM(B2:B6) -> 36593500

Sheet Planeación.
A1: ITEM | B1: ACTIVIDAD | C1: EVIDENCIA | D1: RESPONSABLE | E1: INICIO | F1: FIN
A2: 1 | B2: ESPECIFICACION DE REQUICITOS
A3: 1.1. | B3: ELABORAR EL DIAGRAMA DE PROCESOS | C3: DIAGRAMA DE PROCESOS | D3: Sebastián Loboa | E3: 46059 | F3: 46087
A4: 1.2. | B4: ANALIZAR LOS DATOS RECOLECTADOS PARA DETERMINAR LAS NECESIDADES DEL CLIENTE | C4: DOCUMENTO DE ANALISIS | D4: Bryam Soriano | E4: 46088 | F4: 46097
A5: 1.3. | B5: ELABORAR INFORME DE REQUICITOS DEL SISTEMA | C5: DOCUMENTO IEEE-830 | D5: Daniel Pimienta. | E5: 46098 | F5: 46108
A6: 2 | B6: ANALISIS DE LA ESPECIFICACION DE REQUICITOS
A7: 2.2. | B7: DIAGRAMAR LOS CASOS DE USO | C7: DIAGRAMA DE CASOS DE USO | D7: Bryam Soriano | E7: 46109 | F7: 46117
A8: 2.3. | B8: GENERAR LAS PLANTILLAS DE LOS CASOS DE USO EXTENDIDO | C8: CASOS DE USO ENTENDIDO | D8: Daniel Pimienta. | E8: 46118 | F8: 46128
A9: 2.4. | B9: ELABORAR EL MODELO ENTIDAD RELACION | C9: MER | D9: Sebastián Loboa | E9: 46129 | F9: 46142
A10: 3 | B10: ELABORACIÓN DE LA PROPUESTA TÉCNICA DEL SOFTWARE
A11: 3.1. | B11: Diseñar formatos de fichas técnicas para hardware y software | C11: Fichas técnicas diseñadas según estándares | D11: Bryam Soriano | E11: 46146 | F11: 46153
A12: 3.2. | B12: Estimar costos y presupuestos del software | C12: Análisis comparativo de proveedores y presupuestos | D12: Sebastián Loboa | E12: 46154 | F12: 46162
A13: 3.3. | B13: Construir la propuesta técnica del software | C13: Propuesta técnica documentada | D13: Daniel Pimienta. | E13: 46163 | F13: 46171
A14: 4 | B14: MODELADO DE LOS ARTEFACTOS DEL SOFTWARE
A15: 4.1. | B15: Definir la arquitectura del software (capas, componentes, vistas) | C15: Documento de diseño y arquitectura del software | D15: Sebastián Loboa, Daniel Pimienta | E15: 46174 | F15: 46185
A16: 4.2. | B16: Crear el diagrama de clases y diagramas de componentes | C16: Diagramas UML de clases y vista de componentes | D16: Bryam Soriano | E16: 46188 | F16: 46199
A17: 4.3. | B17: Elaborar prototipos de interfaz gráfica de usuario | C17: Prototipos para aplicaciones stand-alone, web y móviles | D17: Daniel Pimienta. | E17: 46202 | F17: 46209
A18: 5 | B18: CONSTRUCCIÓN DEL SOFTWARE
A19: 5.1. | B19: Implementar la base de datos física a partir del modelo | C19: Base de datos funcional con objetos y restricciones | D19: Sebastián Loboa. | E19: 46213 | F19: 46248
A20: 5.2. | B20: Crear componentes front-end de acuerdo con el diseño | C20: Interfaces de usuario front-end codificadas | D20: Bryam Soriano | E20: 46251 | F20: 46283
A21: 5.3. | B21: Codificar los módulos del software (stand- alone, web y móvil) | C21: Módulos de software integrados y codificados | D21: Daniel Pimienta. | E21: 46286 | F21: 46325
A22: 5.4. | B22: Realizar pruebas de funcionalidad al software | C22: Informe de pruebas y casos de prueba documentados | D22: Daniel Pimienta. | E22: 46328 | F22: 46339
A23: 6 | B23: IMPLANTACIÓN DEL SOFTWARE
A24: 6.1. | B24: Configurar el software y servicios en el servidor de producción | C24: Aplicación publicada y operativa en la plataforma | D24: Sebastián Loboa. | E24: 46342 | F24: 46346
A25: 6.2. | B25: Elaborar manuales técnicos, de usuario y de instalación | C25: Manuales de usuario, técnicos y de instalación | D25: Daniel Pimienta. | E25: 46349 | F25: 46356
A26: 6.3. | B26: Capacitar a los usuarios en el uso del software | C26: Registro de capacitación y acta de entrega formal | D26: Daniel Pimienta. | E26: 46357 | F26: 46360
A27: 7 | B27: ADOPCIÓN DE BUENAS PRÁCTICAS EN EL DESARROLLO
A28: 7.1. | B28: Aplicar el proceso personal de desarrollo de software (PSP) | C28: Registro de actividades y bitácora de trabajo (Libro) | D28: Sebastián Loboa. | E28: 46363 | F28: 46365
A29: 7.2. | B29: Verificar y evaluar la calidad del software desarrollado | C29: Informe de evaluación de la calidad y bitácora de lecciones | D29: Daniel Pimienta. | E29: 46366 | F29: 46368

Sheet Gastos Administrativos.
D1: Total de Gastos Admnistrativos por los 18 meses
A2: Concepto | B2: Detalle de Aplicación | C2: Subtotal /Mes(COP) | D2: Tiempo del Proyecto(meses)
A3: Servicios Públicos e Internet | B3: Conectividad, energía, agua. | C3: =SUM(C16:C18) -> 550000 | D3: =C3*18 -> 9900000
A4: Papelería y Suministros | B4: Documentación física. | C4: 50000 | D4: =C4*18 -> 900000
B5: Total | C5: =SUM(C3:C4) -> 600000
B11: Total Gastos Administrativos. | D11: Margen Neto | F11: Margen Bruto
B12: =SUM(D3:D4) -> 10800000 | D12: =F12/10000000 -> 1.65935 | F12: =26593500-10000000 -> 16593500
B15: Servicios y Conectividad. | C15: Precios | D15: Margen de Utilidad
B16: Internet Fibra óptica | C16: 150000 | D16: =F12/D12 -> 10000000
B17: Servicio Agua | C17: 250000
B18: Servicio Luz | C18: 150000
B20: Documentación | C20: Precios.
B21: Por documento imprimido. | C21: 5000

Sheet Recursos Humanos.
A1: Nombre del Profesional | B1: Rol Específico | C1: Meses | D1: Ganacia/Hora | E1: Ganancia/Día. | F1: Valor Mensual | G1: Total Salario
A2: Daniel | B2: Líder de Proyecto / Analista | C2: 18 | D2: =F2/F13 -> 1282.0513 | E2: =F2/D16 -> 125000 | F2: 2500000 | G2: =E2*D16 -> 2500000
A3: Bryan | B3: Desarrollador Backend | C3: 18 | D3: =F3/F13 -> 1282.0513 | E3: =F3/D16 -> 125000 | F3: 2500000 | G3: =E3*D16 -> 2500000
A4: Sebastian | B4: QA / Gestor de Base de Datos | C4: 18 | D4: =F4/F13 -> 1282.0513 | E4: =F4/D16 -> 125000 | F4: 2500000 | G4: =E4*D16 -> 2500000
A5: Total Talento Humano | G5: =SUM(G2,G3,G4) -> 7500000
B9: 18 Meses en Días. | D9: Horas trabajadas al día.
B10: 547 | D10: 5
D12: Días Trabajados de la semana | F12: Horas Durante Todo el Proyecto.
D13: 5 | F13: =D19*F16 -> 1950
D15: Días Trabajados al mes | F15: Equivalente de meses Trabajados en semanas.
D16: 20 | F16: 78
D18: Horas Trabajadas Semanales | F18: Días Trabajados durante todo el proyecto.
D19: =D10*D13 -> 25 | F19: =D16*C2 -> 360

Sheet Hadware.
A2: Concepto | B2: Detalle de Equipos. | C2: Subtotal (COP)
A3: Depreciación de Equipos | B3: Desgaste de hardware de desarrollo (18 meses).
A4: Total Administrativo | B4: Computador 1 | C4: =(E14-F30)/E19 -> 562500
B5: Computador 2 | C5: =(E15-F31)/E20 -> 562500
B6: Computador 3 | C6: =(E16-F32)/E21 -> 562500
C7: =SUM(C4:C6) -> 1687500
B13: Información de la depreciación de los equipos de desarrollo. | D13: Computadores | E13: Precio.
B14: Se hace la depreción de los equipos basado en el precio inicial del equipo, menos el valor residual del tiempo de uso(es decir, precio que se le atribuye por uso de cada año), sobre la vida útil estimada. | D14: 1 | E14: 2500000
D15: 2 | E15: 2500000
D16: 3 | E16: 2500000
B17: Valor Residual.
B18: Representa el valor de depreciación del equipo por año, se calcula a partir del costo total inicial del equipo, entre el porcentaje de depreciación anual(valor residual). El valor residual varia dependiendo de las normas tributarias del país(en caso de Colombia es de un 20 porciento) | D18: Vida útil estimada de cada computador | E18: Años
D19: 1 | E19: 4
D20: 2 | E20: 4
D21: 3 | E21: 4
D23: Computador. | E23: Valor Residual Por año(Aproximadamente de un 1 año ) | F23: Valor Residual.
D24: 1 | E24: 1 | F24: =E14/20 -> 125000
D25: 2 | E25: 1 | F25: =E15/20 -> 125000
D26: 3 | E26: 1 | F26: =E16/20 -> 125000
D29: Computador. | E29: Valor Residual Por año(Aproximadamente de 2 años ) | F29: Valor Residual.
D30: 1 | E30: 2 | F30: =F24*E30 -> 250000
D31: 2 | E31: 2 | F31: =F25*E31 -> 250000
D32: 3 | E32: 2 | F32: =F26*E32 -> 250000

Sheet Software.
A1: Ítem | B1: Descripción Técnica | C1: Proyección (18 meses) | E1: Subtotal (COP)
A2: Hosting (Alojamiento) | B2: Servidor virtual para despliegue de la aplicación.(Google Cloud/ Azure) | C2: =C34 -> 367000 | E2: =C2*C11 -> 6606000
A4: Dominio (DNS) | B4: Registro y renovación anual de identidad web. | C4: Adquisición | E4: 0
A5: Total Software | E5: =SUM(E2:E4) -> 6606000
C10: Meses de Trabajo.
C11: 18
E12: Información de Software | F12: El precio total de un servidor, varia dependiendo del almacenamiento que se necesite por consumo(ya sea de manera mensual o anual), basandose en tres elementos.
B15: Elementos de un servidor. | E15: ¿Cómo se calculo? | F15: Las empresas dueñas de los servidores, por lo general traen, un precio determinado, en base a la necesidad del cliente, es decir, cuento almacenamiento requiere. Esto se hace mediante Calculadoras virtuales, donde dependiendo del almacenamiento requirido por cada elemento, se tiene un precio estimado en dolares. Para el caso de SIGAP, se hace la conversión, teniendo en cuenta que se necesita dos servidores: Azure(Base de datos, Backend), google cloud(Frontend)
B16: Elemento | C16: ¿Qué es?
B17: CPU | C17: Es el "cerebro". Procesa las instrucciones y ejecuta el código de las aplicaciones o sitios web. Los servidores requieren procesadores con muchos núcleos para manejar múltiples tareas a la vez.
B20: Memoria | C20: Es el área de trabajo temporal. Almacena los datos que la CPU necesita acceder de inmediato (como bases de datos en ejecución o sesiones de usuarios). Tener mucha RAM evita que el servidor tenga que leer el disco duro constantemente.
B23: Almacenamiento | C23: Es donde se guardan los archivos, el sistema operativo, los programas y las bases de datos de forma permanente. Se mide en Gigabytes o Terabytes
B29: Precio Servidores
B30: Servidor. | C30: Google Cloud
B31: Precio. | C31: 230000
B32: Servidor. | C32: Azure
B33: Precio. | C33: 137000
B34: Total | C34: =C31+C33 -> 367000
